{
  "id": "notification-center-clear-action",
  "name": "notification-center-clear-action",
  "title": "Add notification center clear action",
  "description": "",
  "status": "completed",
  "dev_type": null,
  "scope": null,
  "package": null,
  "priority": "P2",
  "creator": "codex",
  "assignee": "codex",
  "createdAt": "2026-06-12",
  "completedAt": "2026-06-14",
  "branch": null,
  "base_branch": "feature-task",
  "worktree_path": null,
  "commit": null,
  "pr_url": null,
  "subtasks": [],
  "children": [],
  "parent": null,
  "relatedFiles": [],
  "notes": "",
  "meta": {}
}